[{"date": "2026-04-26", "count": 8249}, {"date": "2026-04-27", "count": 8281}, {"date": "2026-04-28", "count": 8307}, {"date": "2026-04-29", "count": 8319}, {"date": "2026-04-30", "count": 8358}, {"date": "2026-05-01", "count": 8378}, {"date": "2026-05-02", "count": 8386}, {"date": "2026-05-03", "count": 8397}, {"date": "2026-05-04", "count": 8410}, {"date": "2026-05-05", "count": 8425}, {"date": "2026-05-06", "count": 8437}, {"date": "2026-05-07", "count": 8453}, {"date": "2026-05-08", "count": 8458}, {"date": "2026-05-09", "count": 8470}, {"date": "2026-05-10", "count": 8478}, {"date": "2026-05-11", "count": 8486}, {"date": "2026-05-12", "count": 8495}, {"date": "2026-05-13", "count": 8514}, {"date": "2026-05-14", "count": 8535}, {"date": "2026-05-15", "count": 8548}, {"date": "2026-05-16", "count": 8563}, {"date": "2026-05-17", "count": 8585}, {"date": "2026-05-18", "count": 8594}, {"date": "2026-05-19", "count": 8612}, {"date": "2026-05-20", "count": 8626}, {"date": "2026-05-21", "count": 8636}, {"date": "2026-05-22", "count": 8647}, {"date": "2026-05-23", "count": 8661}, {"date": "2026-05-24", "count": 8670}, {"date": "2026-05-25", "count": 8678}, {"date": "2026-05-26", "count": 8695}, {"date": "2026-05-27", "count": 8711}, {"date": "2026-05-28", "count": 8711}]